levibes/__init__.py
levibes/__main__.py
levibes/caption_generation.py
levibes/cli.py
levibes/config.py
levibes/generate_images.py
levibes/upload.py
levibes/utils/__init__.py
levibes/utils/file_helpers.py
levibes/utils/logger.py
levibes/utils/validators.py
levibes-0.1.1.dist-info/licenses/LICENSE
levibes-0.1.1.dist-info/METADATA
levibes-0.1.1.dist-info/WHEEL
levibes-0.1.1.dist-info/entry_points.txt
levibes-0.1.1.dist-info/top_level.txt
levibes-0.1.1.dist-info/RECORD
