Metadata-Version: 2.4
Name: levibes
Version: 0.1.1
Summary: Motivational Image Caption Generator - Create inspiring social media content with AI-generated captions
Requires-Python: >=3.12
License-File: LICENSE
Requires-Dist: art
Requires-Dist: boto3>=1.34.0
Requires-Dist: cryptography>=41.0.0
Requires-Dist: gratient
Requires-Dist: openai>=1.93.0
Requires-Dist: pillow>=11.3.0
Requires-Dist: prompt-toolkit>=3.0.51
Requires-Dist: pydantic>=2.11.7
Requires-Dist: python-dotenv>=1.1.1
Requires-Dist: requests>=2.31.0
Requires-Dist: yaspin>=3.1.0
Requires-Dist: flask>=2.3.0
Requires-Dist: werkzeug>=2.3.0
Dynamic: license-file
